djrobots/__init__.py
djrobots/urls.py
djrobots/views.py
djrobots/templates/djrobots/base-robots.txt
djrobots/templates/djrobots/robots-debug.txt
djrobots/templates/djrobots/robots.txt
djrobots/templates/djrobots/sitemap.txt
tests/__init__.py
tests/test_djrobots.py
tests/urls.py
djrobots-0.0.8.dist-info/LICENSE
djrobots-0.0.8.dist-info/METADATA
djrobots-0.0.8.dist-info/WHEEL
djrobots-0.0.8.dist-info/top_level.txt
djrobots-0.0.8.dist-info/RECORD
