Metadata-Version: 2.1
Name: djrobots
Version: 0.0.8
Summary: Django powered cms
Home-page: https://github.com/lotrekagency/djrobots
Author: Lotrèk
Author-email: dimmitutto@lotrek.it
License: MIT
Keywords: cms,django,api cms
Platform: UNKNOWN
Classifier: Environment :: Web Environment
Classifier: Framework :: Django
Classifier: Intended Audience :: Developers
Classifier: Programming Language :: Python
Classifier: Programming Language :: Python :: 3
Requires-Python: >=3.0.*
License-File: LICENSE
